<?xml version="1.0" encoding="utf-8"?>
<!DOCTYPE hibernate-mapping PUBLIC "-//Hibernate/Hibernate Mapping DTD 3.0//EN"
"http://hibernate.sourceforge.net/hibernate-mapping-3.0.dtd">
<!-- 
    Mapping file autogenerated by MyEclipse Persistence Tools
-->
<hibernate-mapping>
    <class name="com.abbcc.pojo.Hysh" table="hysh">
        <id name="glyid" type="java.lang.Integer">
            <column name="glyid" />
            <generator class="native"></generator>
        </id>
        <property name="hyjbxxid" type="java.lang.Integer">
            <column name="hyjbxxid" />
        </property>
        <property name="zcsj" type="java.lang.String">
            <column name="zcsj" length="11" />
        </property>
        <property name="dqsj" type="java.lang.String">
            <column name="dqsj" length="11" />
        </property>
        <property name="zhdlsj" type="java.lang.String">
            <column name="zhdlsj" length="11" />
        </property>
        <property name="wdlts" type="java.lang.String">
            <column name="wdlts" length="16" />
        </property>
        <property name="zhdlip" type="java.lang.String">
            <column name="zhdlip" length="16" />
        </property>
        <property name="sfsh" type="java.lang.String">
            <column name="sfsh" length="1" />
        </property>
        <property name="sfyfx" type="java.lang.String">
            <column name="sfyfx" length="1" />
        </property>
        <property name="dlcs" type="java.lang.String">
            <column name="dlcs" length="10" />
        </property>
        <property name="ksrq" type="java.lang.String">
            <column name="ksrq" length="11" />
        </property>
        <property name="jsrq" type="java.lang.String">
            <column name="jsrq" length="11" />
        </property>
        <property name="cpdjtj" type="java.lang.String">
            <column name="cpdjtj" length="16" />
        </property>
    </class>
</hibernate-mapping>
